hydrophilicity_plot/__init__.py
hydrophilicity_plot/__main__.py
hydrophilicity_plot/hydrophilicity_plot.py
hydrophilicity_plot-0.5.dist-info/METADATA
hydrophilicity_plot-0.5.dist-info/WHEEL
hydrophilicity_plot-0.5.dist-info/entry_points.txt
hydrophilicity_plot-0.5.dist-info/top_level.txt
hydrophilicity_plot-0.5.dist-info/RECORD
